posca/__init__.py
posca/funcs.py
posca/main.py
posca-0.1.0.dist-info/entry_points.txt
posca-0.1.0.dist-info/WHEEL
posca-0.1.0.dist-info/METADATA
posca-0.1.0.dist-info/RECORD
